Metadata-Version: 2.1
Name: masterful-gui
Version: 0.6.0
Summary: Masterful AutoML Platform GUI.
Home-page: https://masterfulai.com
Author: Masterful AI
Author-email: help@masterfulai.com
License: Copyright 2022, Masterful AI, Inc.
Platform: UNKNOWN
Requires-Python: >=3.6
License-File: LICENSE
Requires-Dist: absl-py (==1.0.0)
Requires-Dist: asgiref (==3.4.1)
Requires-Dist: Django (==3.2.8)
Requires-Dist: django-cors-headers (==3.10.0)
Requires-Dist: django-webpack-loader (==1.4.1)
Requires-Dist: djangorestframework (==3.12.4)
Requires-Dist: protobuf (==3.19.0)
Requires-Dist: pytz (==2021.3)
Requires-Dist: six (==1.16.0)
Requires-Dist: sqlparse (==0.4.2)
Requires-Dist: Werkzeug (==2.0.2)
